matrix/fastapi/__init__.py
matrix_zion_fastapi-0.1.0.dist-info/METADATA
matrix_zion_fastapi-0.1.0.dist-info/WHEEL
matrix_zion_fastapi-0.1.0.dist-info/entry_points.txt
matrix_zion_fastapi-0.1.0.dist-info/RECORD
