Metadata-Version: 2.3
Name: matrix-zion-fastapi
Version: 0.1.0
Summary: Extensão FastAPI para o framework Matrix - Plugin para APIs REST
License: MIT
Keywords: microservices,fastapi,matrix,plugin,rest,api
Author: Tuyoshi Vinicius
Author-email: tuyoshi.vinicius@gmail.com
Requires-Python: >=3.10
Classifier: Development Status :: 3 - Alpha
Classifier: Intended Audience :: Developers
Classifier: License :: OSI Approved :: MIT License
Classifier: Programming Language :: Python :: 3
Classifier: Programming Language :: Python :: 3.10
Classifier: Programming Language :: Python :: 3.11
Classifier: Programming Language :: Python :: 3.12
Classifier: Topic :: Software Development :: Libraries :: Python Modules
Classifier: Topic :: Internet :: WWW/HTTP :: HTTP Servers
Provides-Extra: dev
Requires-Dist: fastapi (>=0.100.0)
Requires-Dist: httpx (>=0.24.0) ; extra == "dev"
Requires-Dist: matrix-zion (>=0.1.0)
Requires-Dist: pytest (>=8.0.0) ; extra == "dev"
Requires-Dist: uvicorn (>=0.20.0)
Project-URL: Bug Reports, https://github.com/tuyoshivinicius/python-microservice-v2/issues
Project-URL: Documentation, https://github.com/tuyoshivinicius/python-microservice-v2/blob/main/README.md
Project-URL: Homepage, https://github.com/tuyoshivinicius/python-microservice-v2
Project-URL: Repository, https://github.com/tuyoshivinicius/python-microservice-v2
